jprops.py
jprops-2.0.dist-info/DESCRIPTION.rst
jprops-2.0.dist-info/METADATA
jprops-2.0.dist-info/RECORD
jprops-2.0.dist-info/WHEEL
jprops-2.0.dist-info/metadata.json
jprops-2.0.dist-info/top_level.txt
jprops-2.0.dist-info/zip-safe
