Metadata-Version: 2.0
Name: jprops
Version: 2.0
Summary: Parser for Java .properties files
Home-page: http://github.com/mgood/jprops/
Author: Matt Good
Author-email: matt@matt-good.net
License: BSD
Platform: any
